torusimaging/__init__.py
torusimaging/_version.py
torusimaging/_version.pyi
torusimaging/data.py
torusimaging/jax_helpers.py
torusimaging/model.py
torusimaging/model_helpers.py
torusimaging/model_spline.py
torusimaging/plot.py
torusimaging-0.1.dist-info/METADATA
torusimaging-0.1.dist-info/WHEEL
torusimaging-0.1.dist-info/licenses/LICENSE
torusimaging-0.1.dist-info/RECORD
