Metadata-Version: 2.1
Name: torusimaging
Version: 0.1
Summary: Inferring the Galactic mass distribution with stellar labels
Project-URL: Homepage, https://github.com/adrn/torusimaging
Project-URL: Bug Tracker, https://github.com/adrn/torusimaging/issues
Project-URL: Discussions, https://github.com/adrn/torusimaging/discussions
Project-URL: Changelog, https://github.com/adrn/torusimaging/releases
Author-email: Adrian Price-Whelan <adrianmpw@gmail.com>
License: MIT License
License-File: LICENSE
Keywords: astronomy,dynamics,galactic dynamics
Classifier: Intended Audience :: Developers
Classifier: Intended Audience :: Science/Research
Classifier: License :: OSI Approved :: MIT License
Classifier: Operating System :: OS Independent
Classifier: Programming Language :: Python
Classifier: Programming Language :: Python :: 3
Classifier: Programming Language :: Python :: 3 :: Only
Classifier: Programming Language :: Python :: 3.10
Classifier: Programming Language :: Python :: 3.11
Classifier: Programming Language :: Python :: 3.12
Classifier: Topic :: Scientific/Engineering
Classifier: Typing :: Typed
Requires-Python: >=3.10
Requires-Dist: astropy>=5.1
Requires-Dist: blackjax
Requires-Dist: gala
Requires-Dist: jax
Requires-Dist: jax-cosmo
Requires-Dist: jaxlib
Requires-Dist: jaxopt
Requires-Dist: matplotlib
Requires-Dist: numpy>=1.20
Requires-Dist: pyyaml
Requires-Dist: scipy>=1.9
Provides-Extra: dev
Requires-Dist: pytest-cov>=3; extra == 'dev'
Requires-Dist: pytest>=6; extra == 'dev'
Provides-Extra: docs
Requires-Dist: matplotlib; extra == 'docs'
Requires-Dist: myst-nb; extra == 'docs'
Requires-Dist: pydata-sphinx-theme; extra == 'docs'
Requires-Dist: scipy; extra == 'docs'
Requires-Dist: sphinx-autodoc-typehints; extra == 'docs'
Requires-Dist: sphinx-automodapi; extra == 'docs'
Requires-Dist: sphinx-copybutton; extra == 'docs'
Requires-Dist: sphinx>=7.0; extra == 'docs'
Provides-Extra: test
Requires-Dist: pytest-astropy; extra == 'test'
Requires-Dist: pytest-cov>=3; extra == 'test'
Requires-Dist: pytest>=6; extra == 'test'
Requires-Dist: pyyaml; extra == 'test'
